.bumpversion.cfg
.coveragerc
.travis.yml
AUTHORS
ChangeLog
README.md
requirements.txt
setup.cfg
setup.py
tox.ini
modcov/__init__.py
modcov/__main__.py
modcov.egg-info/PKG-INFO
modcov.egg-info/SOURCES.txt
modcov.egg-info/dependency_links.txt
modcov.egg-info/entry_points.txt
modcov.egg-info/not-zip-safe
modcov.egg-info/pbr.json
modcov.egg-info/requires.txt
modcov.egg-info/top_level.txt
tests/__init__.py
tests/coverage_data
tests/test_modcov.py