Metadata-Version: 1.1
Name: modcov
Version: 0.0.3.dev30
Summary: "A tool to check every module's code coverage."
Home-page: https://github.com/coldnight/modcov
Author: Gray King
Author-email: grayking.w@gmail.com
License: Apache 2.0
Platform: UNKNOWN
Classifier: Development Status :: 3 - Alpha
Classifier: Intended Audience :: Developers
Classifier: License :: OSI Approved :: Apache Software License
Classifier: Programming Language :: Python :: 2.7
Classifier: Programming Language :: Python :: 3.3
Classifier: Programming Language :: Python :: 3.4
Classifier: Programming Language :: Python :: 3.5
Classifier: Programming Language :: Python :: 3.6
